schenesort/__init__.py
schenesort/cli.py
schenesort/config.py
schenesort/db.py
schenesort/xmp.py
schenesort/tui/__init__.py
schenesort/tui/app.py
schenesort/tui/widgets/__init__.py
schenesort/tui/widgets/image_preview.py
schenesort/tui/widgets/metadata_panel.py
schenesort-2.2.0.dist-info/METADATA
schenesort-2.2.0.dist-info/WHEEL
schenesort-2.2.0.dist-info/entry_points.txt
schenesort-2.2.0.dist-info/licenses/LICENSE
schenesort-2.2.0.dist-info/RECORD
