Metadata-Version: 2.4
Name: schenesort
Version: 2.2.0
Summary: Wallpaper collection management CLI tool
License-File: LICENSE
Requires-Python: >=3.13
Requires-Dist: defusedxml>=0.7.1
Requires-Dist: filetype>=1.2.0
Requires-Dist: ollama>=0.6.1
Requires-Dist: textual-image>=0.8.5
Requires-Dist: textual>=0.95.0
Requires-Dist: typer>=0.21.1
